{
    "id":0,
    "code":"ok",
    "status":200,
    "dataInfo":[{
        "id":0,
        "name":"全部类目",
        "child":[{
            "id":0,
            "name":"三只羊阳坊涮羊肉",
            "price":"105",
            "address":"上地163m",
            "tit":"羊蝎子",
            "img":"img/6.jpg",
            "start":4,
            "out":""
        },{
            "id":1,
            "name":"小城外婆肴私房菜(上地店)",
            "price":"46",
            "address":"上地269m",
            "tit":"私房菜",
            "img":"img/7.jpg",
            "start":5,
            "out":"支持外卖|预订"
        },{
            "id":2,
            "name":"三只羊阳坊涮羊肉2",
            "price":"105",
            "address":"上地163m",
            "tit":"羊蝎子",
            "img":"img/8.png",
            "start":5,
            "out":"支持外卖|预订"
        },{
            "id":3,
            "name":"三只羊阳坊涮羊肉2",
            "price":"105",
            "address":"上地163m",
            "tit":"羊蝎子",
            "img":"img/8.png",
            "start":5,
            "out":"支持外卖|预订"
        },{
            "id":4,
            "name":"三只羊阳坊涮羊肉2",
            "price":"105",
            "address":"上地163m",
            "tit":"羊蝎子",
            "img":"img/8.png",
            "start":5,
            "out":"支持外卖|预订"
        },{
            "id":5,
            "name":"三只羊阳坊涮羊肉2",
            "price":"105",
            "address":"上地163m",
            "tit":"羊蝎子",
            "img":"img/8.png",
            "start":5,
            "out":"支持外卖|预订"
        },{
            "id":6,
            "name":"三只羊阳坊涮羊肉2",
            "price":"105",
            "address":"上地163m",
            "tit":"羊蝎子",
            "img":"img/8.png",
            "start":5,
            "out":"支持外卖|预订"
        }]
    },{
        "id":1,
        "name":"附近商家",
        "child":[]
    },{
        "id":2,
        "name":"智能排序",
        "child":[]
    },{
        "id":3,
        "name":"筛选",
        "child":[]
    }]
}